mason_xt_data/__init__.py
mason_xt_data/xt_data_client.py
mason_xt_data/xt_data_server.py
mason_xt_data-0.1.16.dist-info/METADATA
mason_xt_data-0.1.16.dist-info/WHEEL
mason_xt_data-0.1.16.dist-info/top_level.txt
mason_xt_data-0.1.16.dist-info/RECORD
