Metadata-Version: 2.1
Name: mason-xt-data
Version: 0.1.16
Summary: mason_xt_data.
Author: mason
License: MIT
Requires-Python: >=3.7
Requires-Dist: mason-tools
Requires-Dist: pandas
